<?xml version="1.0" encoding="utf-8"?>
<ScrollView xmlns:android="http://schemas.android.com/apk/res/android"
    xmlns:app="http://schemas.android.com/apk/res-auto"
    android:orientation="vertical"
    android:layout_width="match_parent"
    android:layout_height="match_parent">
  <LinearLayout
      android:orientation="vertical"
      android:padding="20dp"
      android:layout_width="match_parent"
      android:layout_height="wrap_content">
    <TextView
          android:text="Why do you need this app for?"
          android:layout_width="match_parent"
          android:layout_height="wrap_content"/>
    <RadioGroup
        android:orientation="vertical"
        android:layout_width="match_parent"
        android:layout_height="wrap_content">
      <RadioButton
          android:text="I'm looking for work"
          android:layout_width="wrap_content"
          android:layout_height="wrap_content"/>
      <RadioButton
          android:text="I need help with something"
          android:layout_width="wrap_content"
          android:layout_height="wrap_content"/>
    </RadioGroup>
    <Space
        android:layout_width="match_parent"
        android:layout_height="10dp"/>
    <View
        android:background="@color/black"
        android:layout_width="match_parent"
        android:layout_height="1dp"/>
    <Space
        android:layout_width="match_parent"
        android:layout_height="10dp"/>
    <android.support.design.widget.TextInputLayout
        android:layout_width="match_parent"
        android:layout_height="wrap_content"
        android:hint="Last Name">
      <android.support.design.widget.TextInputEditText
          style="@style/EditTextStyle"
          android:layout_width="match_parent"
          android:layout_height="wrap_content"/>
    </android.support.design.widget.TextInputLayout>
    <android.support.design.widget.TextInputLayout
        android:layout_width="match_parent"
        android:layout_height="wrap_content"
        android:hint="First Name">
      <android.support.design.widget.TextInputEditText
          style="@style/EditTextStyle"
          android:layout_width="match_parent"
          android:layout_height="wrap_content"/>
    </android.support.design.widget.TextInputLayout>
    <android.support.design.widget.TextInputLayout
        android:layout_width="match_parent"
        android:layout_height="wrap_content"
        android:hint="Middle">
      <android.support.design.widget.TextInputEditText
          style="@style/EditTextStyle"
          android:layout_width="match_parent"
          android:layout_height="wrap_content"/>
    </android.support.design.widget.TextInputLayout>
    <android.support.design.widget.TextInputLayout
          android:layout_width="match_parent"
          android:layout_height="wrap_content"
          android:hint="Age">
      <android.support.design.widget.TextInputEditText
          style="@style/EditTextStyle"
          android:inputType="number"
          android:layout_width="50dp"
          android:layout_height="wrap_content"/>
    </android.support.design.widget.TextInputLayout>
    <Space
        android:layout_width="match_parent"
        android:layout_height="10dp"/>
    <TextView
        android:text="Gender"
        android:layout_width="match_parent"
        android:layout_height="wrap_content"/>
    <RadioGroup
        android:orientation="horizontal"
        android:layout_width="match_parent"
        android:layout_height="wrap_content">
      <RadioButton
          android:text="Male"
          android:layout_width="wrap_content"
          android:layout_height="wrap_content"/>
      <RadioButton
          android:text="Female"
          android:layout_width="wrap_content"
          android:layout_height="wrap_content"/>
    </RadioGroup>
    <Space
        android:layout_width="match_parent"
        android:layout_height="10dp"/>
    <TextView
        android:text="Expertise"
        android:layout_width="match_parent"
        android:layout_height="wrap_content"/>
    <Spinner
        android:id="@+id/expertise_spin"
        style="@style/Widget.AppCompat.Spinner.Underlined"
        android:spinnerMode="dropdown"
        android:layout_width="match_parent"
        android:layout_height="wrap_content"/>
    <android.support.design.widget.TextInputLayout
          android:layout_width="match_parent"
          android:layout_height="wrap_content"
          android:hint="Unionbank Account No.">
      <android.support.design.widget.TextInputEditText
          style="@style/EditTextStyle"
          android:inputType="number"
          android:layout_width="match_parent"
          android:layout_height="wrap_content"/>
    </android.support.design.widget.TextInputLayout>
    <LinearLayout
        android:orientation="horizontal"
        android:gravity="right"
        android:layout_width="match_parent"
        android:layout_height="wrap_content">
      <Button
          android:id="@+id/done_btn"
          android:text="Done"
          android:textColor="@color/white"
          android:layout_width="wrap_content"
          android:layout_height="wrap_content"/>
    </LinearLayout>
  </LinearLayout>
</ScrollView>